reqs_checker/__init__.py
reqs_checker/checker.py
reqs_checker-1.0.0.dist-info/LICENSE
reqs_checker-1.0.0.dist-info/METADATA
reqs_checker-1.0.0.dist-info/WHEEL
reqs_checker-1.0.0.dist-info/entry_points.txt
reqs_checker-1.0.0.dist-info/top_level.txt
reqs_checker-1.0.0.dist-info/RECORD
