Metadata-Version: 2.1
Name: reqs-checker
Version: 1.0.0
Summary: A tool to check installed Python package versions against requirements.txt and PyPI.
Home-page: https://github.com/BenevolenceMessiah/reqs-checker
Author: Benevolence Messiah
Author-email: Benevolence Messiah <benevolence.messiah@gmail.com>
License: MIT
Project-URL: Homepage, https://github.com/BenevolenceMessiah/reqs-checker
Project-URL: Repository, https://github.com/BenevolenceMessiah/reqs-checker
Classifier: Programming Language :: Python :: 3
Classifier: License :: OSI Approved :: MIT License
Classifier: Operating System :: OS Independent
Requires-Python: >=3.7
License-File: LICENSE
Requires-Dist: requests>=2.28.0
Requires-Dist: packaging>=21.0
